README.md
setup.py
woof/__init__.py
woof/common.py
woof/consumer.py
woof/green_consumer.py
woof/partitioned_producer.py
woof/producer.py
woof/transactions.py
woof3.egg-info/PKG-INFO
woof3.egg-info/SOURCES.txt
woof3.egg-info/dependency_links.txt
woof3.egg-info/requires.txt
woof3.egg-info/top_level.txt