Metadata-Version: 1.1
Name: woof3
Version: 3.1
Summary: Messaging library 
Home-page: UNKNOWN
Author: Jyotiswarup Raiturkar
Author-email: jyotisr5@gmail.com
License: UNKNOWN
Keywords: apache kafka
Platform: UNKNOWN
Classifier: Development Status :: 3 - Alpha
Classifier: Intended Audience :: Developers
Classifier: Programming Language :: Python
Classifier: Programming Language :: Python :: 2
Classifier: Programming Language :: Python :: 2.6
Classifier: Programming Language :: Python :: 2.7
Classifier: Programming Language :: Python :: 3
Classifier: Programming Language :: Python :: Implementation :: PyPy
Classifier: Topic :: Software Development :: Libraries :: Python Modules
